LICENSE
MANIFEST.in
README.rst
requirements.txt
setup.py
docs/Makefile
docs/conf.py
docs/index.rst
docs/make.bat
docs/apis/changelog.rst
docs/apis/core.rst
docs/apis/neurons.rst
docs/apis/synapses.rst
docs/apis/usage_of_inputfactory.py
docs/apis/usage_of_utils_connect.py
docs/apis/usage_of_utils_connect.rst
docs/apis/utils.rst
docs/apis/.ipynb_checkpoints/usage_of_utils_connect-checkpoint.py
docs/apis/.ipynb_checkpoints/utils_input_factory-checkpoint.py
docs/apis/_autosummary/npbrain.core.Euler_method.rst
docs/apis/_autosummary/npbrain.core.Heun_method.rst
docs/apis/_autosummary/npbrain.core.Milstein_dfree_Ito.rst
docs/apis/_autosummary/npbrain.core.Milstein_dfree_Stra.rst
docs/apis/_autosummary/npbrain.core.backward_Euler.rst
docs/apis/_autosummary/npbrain.core.firing_rate.rst
docs/apis/_autosummary/npbrain.core.format_delay.rst
docs/apis/_autosummary/npbrain.core.format_geometry.rst
docs/apis/_autosummary/npbrain.core.format_refractory.rst
docs/apis/_autosummary/npbrain.core.forward_Euler.rst
docs/apis/_autosummary/npbrain.core.generate_fake_neuron.rst
docs/apis/_autosummary/npbrain.core.initial_neu_state.rst
docs/apis/_autosummary/npbrain.core.initial_syn_state.rst
docs/apis/_autosummary/npbrain.core.integrate.rst
docs/apis/_autosummary/npbrain.core.judge_spike.rst
docs/apis/_autosummary/npbrain.core.midpoint.rst
docs/apis/_autosummary/npbrain.core.ode_backward_euler.rst
docs/apis/_autosummary/npbrain.core.ode_euler.rst
docs/apis/_autosummary/npbrain.core.ode_exponential_euler.rst
docs/apis/_autosummary/npbrain.core.ode_heun.rst
docs/apis/_autosummary/npbrain.core.ode_rk2.rst
docs/apis/_autosummary/npbrain.core.ode_rk3.rst
docs/apis/_autosummary/npbrain.core.ode_rk4.rst
docs/apis/_autosummary/npbrain.core.ode_rk4_alternative.rst
docs/apis/_autosummary/npbrain.core.raster_plot.rst
docs/apis/_autosummary/npbrain.core.record_conductance.rst
docs/apis/_autosummary/npbrain.core.rk2.rst
docs/apis/_autosummary/npbrain.core.rk3.rst
npbrain.egg-info/PKG-INFO
npbrain.egg-info/SOURCES.txt
npbrain.egg-info/dependency_links.txt
npbrain.egg-info/requires.txt
npbrain.egg-info/top_level.txt
